{
    "endDate": "2017-05-03-05:00", 
    "enrollmentStatus": "Open", 
    "href": "/2017/spring/EPS/570/64988.json", 
    "id": "64988", 
    "meetings": {
        "meeting": {
            "daysOfTheWeek": "R", 
            "end": "02:50 PM", 
            "id": "0", 
            "instructors": {
                "instructor": {
                    "content": "McCarthy, C", 
                    "firstName": "C", 
                    "lastName": "McCarthy"
                }
            }, 
            "start": "12:00 PM", 
            "type": {
                "code": "LCD", 
                "content": "Lecture-Discussion"
            }
        }
    }, 
    "parents": {
        "calendarYear": {
            "content": "2017", 
            "href": "/2017.json", 
            "id": "2017"
        }, 
        "course": {
            "content": "Postcolonial Theory & Methodology", 
            "href": "/2017/spring/EPS/570.json", 
            "id": "570"
        }, 
        "subject": {
            "content": "Educational Policy Studies", 
            "href": "/2017/spring/EPS.json", 
            "id": "EPS"
        }, 
        "term": {
            "content": "Spring 2017", 
            "href": "/2017/spring.json", 
            "id": "120171"
        }
    }, 
    "partOfTerm": "1", 
    "sectionNumber": "A", 
    "sectionStatusCode": "A", 
    "startDate": "2017-01-17-06:00", 
    "statusCode": "A"
}