{
    "courseSectionInformation": "Prerequisite: THEA 371, THEA 372, THEA 373, and THEA 374, and concurrent registration in THEA 375, THEA 376 and THEA 377.", 
    "creditHours": "3 hours.", 
    "description": "Development of acting skills for musical theatre including dance, singing, and the analysis of British and American musical theatre materials. A performance is given at the end of the term. Enrollment limited to Theatre majors.Prerequisite: THEA 371, THEA 372, THEA 373, and THEA 374, and concurrent registration in THEA 375, THEA 376 and THEA 377.", 
    "href": "/2017/spring/THEA/378.json", 
    "id": "THEA 378", 
    "label": "Acting Studio II: Acting", 
    "parents": {
        "calendarYear": {
            "content": "2017", 
            "href": "/2017.json", 
            "id": "2017"
        }, 
        "subject": {
            "content": "Theatre", 
            "href": "/2017/spring/THEA.json", 
            "id": "THEA"
        }, 
        "term": {
            "content": "Spring 2017", 
            "href": "/2017/spring.json", 
            "id": "120171"
        }
    }, 
    "sectionRegistrationNotes": "Restricted to students with Sophomore, Junior, or Senior class standing. Restricted to BFA:Theatre: Acting -UIUC.", 
    "sections": {
        "section": {
            "content": "A", 
            "href": "/2017/spring/THEA/378/40147.json", 
            "id": "40147"
        }
    }
}