{"href": "http://courses.illinois.edu/cisapp/explorer/schedule/2017/spring/NPRE/558.xml", "id": "NPRE 558", "parents": {"calendarYear": {"href": "http://courses.illinois.edu/cisapp/explorer/schedule/2017.xml", "id": "2017", "content": "2017"}, "term": {"href": "http://courses.illinois.edu/cisapp/explorer/schedule/2017/spring.xml", "id": "120171", "content": "Spring 2017"}, "subject": {"href": "http://courses.illinois.edu/cisapp/explorer/schedule/2017/spring/NPRE.xml", "id": "NPRE", "content": "Nuclear, Plasma, and Radiological Engineering"}}, "label": "Advanced Design in NPRE", "description": "Classroom exercise in the conceptual design of a nuclear engineering system involving a synthesis of previous learning in the field of nuclear engineering and related disciplines. The design includes all necessary ingredients for the system, such as core, thermal-hydraulics, shielding, material selection, and control. Prerequisite: NPRE 448 and NPRE 501.", "creditHours": "4 hours.", "courseSectionInformation": "Prerequisite: NPRE 448 and NPRE 501.", "sectionRegistrationNotes": "Restricted to Graduate - Urbana-Champaign.", "sections": {"section": {"href": "http://courses.illinois.edu/cisapp/explorer/schedule/2017/spring/NPRE/558/34932.xml", "id": "34932", "content": "A"}}}