{"href": "http://courses.illinois.edu/cisapp/explorer/schedule/2017/spring/PS/322.xml", "id": "PS 322", "parents": {"calendarYear": {"href": "http://courses.illinois.edu/cisapp/explorer/schedule/2017.xml", "id": "2017", "content": "2017"}, "term": {"href": "http://courses.illinois.edu/cisapp/explorer/schedule/2017/spring.xml", "id": "120171", "content": "Spring 2017"}, "subject": {"href": "http://courses.illinois.edu/cisapp/explorer/schedule/2017/spring/PS.xml", "id": "PS", "content": "Political Science"}}, "label": "Law and Public Policy", "description": "Examines the nature of law, law makers, and law appliers; the determinants of law-making; and the societal impact of law. Prerequisite: PS 101, six hours of Political Science credit, or consent of instructor.", "creditHours": "3 hours.", "courseSectionInformation": "Prerequisite: PS 101, six hours of Political Science credit, or consent of instructor.", "sectionRegistrationNotes": "Not intended for students with Freshman class standing.", "sections": {"section": {"href": "http://courses.illinois.edu/cisapp/explorer/schedule/2017/spring/PS/322/39980.xml", "id": "39980", "content": "A"}}}