{"href": "http://courses.illinois.edu/cisapp/explorer/schedule/2017/spring/CATL/402.xml", "id": "CATL 402", "parents": {"calendarYear": {"href": "http://courses.illinois.edu/cisapp/explorer/schedule/2017.xml", "id": "2017", "content": "2017"}, "term": {"href": "http://courses.illinois.edu/cisapp/explorer/schedule/2017/spring.xml", "id": "120171", "content": "Spring 2017"}, "subject": {"href": "http://courses.illinois.edu/cisapp/explorer/schedule/2017/spring/CATL.xml", "id": "CATL", "content": "Catalan"}}, "label": "Studies in Catalan Literature", "description": "Studies selected aspects of Catalan literature; taught in Catalan. Topics will be selected from among the major chronological periods and genres of Catalan literature; such as 20th century novel, Ramon Llull and Ausias March. The intention is to offer the student an in-depth view instead of an introductory overview. 3 undergraduate hours. 3 graduate hours. May be repeated to a maximum of 6 hours if topics vary. Prerequisite: CATL 401 or equivalent.", "creditHours": "3 hours.", "courseSectionInformation": "3 undergraduate hours. 3 graduate hours. May be repeated to a maximum of 6 hours if topics vary. Prerequisite: CATL 401 or equivalent.", "sections": {"section": {"href": "http://courses.illinois.edu/cisapp/explorer/schedule/2017/spring/CATL/402/53378.xml", "id": "53378", "content": "I"}}}