{"href": "http://courses.illinois.edu/cisapp/explorer/schedule/2017/spring/HIST/251.xml", "id": "HIST 251", "parents": {"calendarYear": {"href": "http://courses.illinois.edu/cisapp/explorer/schedule/2017.xml", "id": "2017", "content": "2017"}, "term": {"href": "http://courses.illinois.edu/cisapp/explorer/schedule/2017/spring.xml", "id": "120171", "content": "Spring 2017"}, "subject": {"href": "http://courses.illinois.edu/cisapp/explorer/schedule/2017/spring/HIST.xml", "id": "HIST", "content": "History"}}, "label": "Warfare Milit Insts & Soc", "description": "History of warfare and its relationship to changing technologies, tactics, and political structures, with an emphasis on the ways that military institutions are integrated with society as a whole. Same as GLBL 251.", "creditHours": "3 hours.", "courseSectionInformation": "Same as GLBL 251.", "sectionRegistrationNotes": "Restricted to Undergrad - Urbana-Champaign.", "sections": {"section": {"href": "http://courses.illinois.edu/cisapp/explorer/schedule/2017/spring/HIST/251/34134.xml", "id": "34134", "content": "A"}}}