{
    "courseSectionInformation": "May be repeated if topics vary. Prerequisite: A Greek proseminar.", 
    "creditHours": "4 hours.", 
    "description": "Research on special problems of Greek literature; required of all majors in classical philology. May be repeated if topics vary. Prerequisite: A Greek proseminar.", 
    "href": "/2017/spring/GRK/580.json", 
    "id": "GRK 580", 
    "label": "Greek Seminar", 
    "parents": {
        "calendarYear": {
            "content": "2017", 
            "href": "/2017.json", 
            "id": "2017"
        }, 
        "subject": {
            "content": "Greek", 
            "href": "/2017/spring/GRK.json", 
            "id": "GRK"
        }, 
        "term": {
            "content": "Spring 2017", 
            "href": "/2017/spring.json", 
            "id": "120171"
        }
    }, 
    "sections": {
        "section": {
            "content": "A", 
            "href": "/2017/spring/GRK/580/33626.json", 
            "id": "33626"
        }
    }
}