{
    "endDate": "2017-05-03-05:00", 
    "enrollmentStatus": "Open (Restricted)", 
    "href": "/2017/spring/ACE/161/30493.json", 
    "id": "30493", 
    "meetings": {
        "meeting": {
            "buildingName": "ACES Lib, Info & Alum Ctr", 
            "daysOfTheWeek": "T", 
            "end": "02:50 PM", 
            "id": "0", 
            "instructors": {
                "instructor": {
                    "content": "Rogalla, V", 
                    "firstName": "V", 
                    "lastName": "Rogalla"
                }
            }, 
            "roomNumber": "23", 
            "start": "01:00 PM", 
            "type": {
                "code": "LBD", 
                "content": "Laboratory-Discussion"
            }
        }
    }, 
    "parents": {
        "calendarYear": {
            "content": "2017", 
            "href": "/2017.json", 
            "id": "2017"
        }, 
        "course": {
            "content": "Microcomputer Applications", 
            "href": "/2017/spring/ACE/161.json", 
            "id": "161"
        }, 
        "subject": {
            "content": "Agricultural and Consumer Economics", 
            "href": "/2017/spring/ACE.json", 
            "id": "ACE"
        }, 
        "term": {
            "content": "Spring 2017", 
            "href": "/2017/spring.json", 
            "id": "120171"
        }
    }, 
    "partOfTerm": "1", 
    "sectionNumber": "R", 
    "sectionStatusCode": "A", 
    "sectionText": "Priority registration for College of ACES students until November 21 at 10am.", 
    "startDate": "2017-01-17-06:00", 
    "statusCode": "A"
}