{"href": "http://courses.illinois.edu/cisapp/explorer/schedule/2017/spring/REES/596.xml", "id": "REES 596", "parents": {"calendarYear": {"href": "http://courses.illinois.edu/cisapp/explorer/schedule/2017.xml", "id": "2017", "content": "2017"}, "term": {"href": "http://courses.illinois.edu/cisapp/explorer/schedule/2017/spring.xml", "id": "120171", "content": "Spring 2017"}, "subject": {"href": "http://courses.illinois.edu/cisapp/explorer/schedule/2017/spring/REES.xml", "id": "REES", "content": "Russian, East European and Eurasian Studies"}}, "label": "Topics in REEE Studies", "description": "Topics in the interdisciplinary study of Russia, Eastern Europe, and Eurasia.  May be repeated to a maximum of 12 graduate hours.", "creditHours": "4 hours.", "courseSectionInformation": "May be repeated to a maximum of 12 graduate hours.", "sections": {"section": [{"href": "http://courses.illinois.edu/cisapp/explorer/schedule/2017/spring/REES/596/41797.xml", "id": "41797", "content": "A4"}, {"href": "http://courses.illinois.edu/cisapp/explorer/schedule/2017/spring/REES/596/47161.xml", "id": "47161", "content": "RE"}]}}