{
    "endDate": "2017-05-03-05:00", 
    "enrollmentStatus": "Open", 
    "href": "/2017/spring/PSYC/301/39643.json", 
    "id": "39643", 
    "meetings": {
        "meeting": {
            "daysOfTheWeek": "F", 
            "end": "11:50 AM", 
            "id": "0", 
            "instructors": {
                "instructor": {
                    "content": "Koehn, H", 
                    "firstName": "H", 
                    "lastName": "Koehn"
                }
            }, 
            "start": "10:00 AM", 
            "type": {
                "code": "LAB", 
                "content": "Laboratory"
            }
        }
    }, 
    "parents": {
        "calendarYear": {
            "content": "2017", 
            "href": "/2017.json", 
            "id": "2017"
        }, 
        "course": {
            "content": "Psychological Statistics", 
            "href": "/2017/spring/PSYC/301.json", 
            "id": "301"
        }, 
        "subject": {
            "content": "Psychology", 
            "href": "/2017/spring/PSYC.json", 
            "id": "PSYC"
        }, 
        "term": {
            "content": "Spring 2017", 
            "href": "/2017/spring.json", 
            "id": "120171"
        }
    }, 
    "partOfTerm": "1", 
    "sectionNumber": "AB1", 
    "sectionStatusCode": "A", 
    "startDate": "2017-01-17-06:00", 
    "statusCode": "A"
}