{
    "courseSectionInformation": "Approved for both letter and S/U grading. Prerequisite: Good standing in the veterinary professional curriculum, Graduate College, or consent of instructor.", 
    "creditHours": "1 hours.", 
    "description": "Designed to familiarize veterinary students with the basic principles of equine husbandry, including biosecurity, infectious disease prevention, anti-parasite programs, dental care, transport, and nutrition. Approved for both letter and S/U grading. Prerequisite: Good standing in the veterinary professional curriculum, Graduate College, or consent of instructor.", 
    "href": "/2017/spring/VCM/608.json", 
    "id": "VCM 608", 
    "label": "Equine Veterinary Husbandry", 
    "parents": {
        "calendarYear": {
            "content": "2017", 
            "href": "/2017.json", 
            "id": "2017"
        }, 
        "subject": {
            "content": "Veterinary Clinical Medicine", 
            "href": "/2017/spring/VCM.json", 
            "id": "VCM"
        }, 
        "term": {
            "content": "Spring 2017", 
            "href": "/2017/spring.json", 
            "id": "120171"
        }
    }, 
    "sectionDateRange": "Meets 17-Jan-17 - 10-Mar-17.", 
    "sectionRegistrationNotes": "Restricted to VetMed - Urbana-Champaign.", 
    "sections": {
        "section": {
            "content": "E", 
            "href": "/2017/spring/VCM/608/53825.json", 
            "id": "53825"
        }
    }
}