{"href": "http://courses.illinois.edu/cisapp/explorer/schedule/2017/spring/BADM/515.xml", "id": "BADM 515", "parents": {"calendarYear": {"href": "http://courses.illinois.edu/cisapp/explorer/schedule/2017.xml", "id": "2017", "content": "2017"}, "term": {"href": "http://courses.illinois.edu/cisapp/explorer/schedule/2017/spring.xml", "id": "120171", "content": "Spring 2017"}, "subject": {"href": "http://courses.illinois.edu/cisapp/explorer/schedule/2017/spring/BADM.xml", "id": "BADM", "content": "Business Administration"}}, "label": "Oral Comm for Business", "description": "This class builds communication skills for the English language business environment for international students. It includes work on pronunciation deficits, but also units on broader communication topics, including social interaction skills, appropriate business language, interviewing, and presentations. The class incorporates workshops on specific scenarios such as making a sales pitch, delivering an annual report, handling the press, presenting a case study, communicating during a crisis, and communicating in specific contexts such as within technology, entrepreneur or venture capital fairs. 4 graduate hours. No professional credit. Prerequisite: MSTM students.", "creditHours": "4 hours.", "courseSectionInformation": "4 graduate hours. No professional credit. Prerequisite: MSTM students.", "sectionRegistrationNotes": "Restricted to MS: Technology Management-UIUC.", "sections": {"section": {"href": "http://courses.illinois.edu/cisapp/explorer/schedule/2017/spring/BADM/515/65327.xml", "id": "65327", "content": "A"}}}