{"href": "http://courses.illinois.edu/cisapp/explorer/schedule/2017/spring/MATH/595/63212.xml", "id": "63212", "parents": {"calendarYear": {"href": "http://courses.illinois.edu/cisapp/explorer/schedule/2017.xml", "id": "2017", "content": "2017"}, "term": {"href": "http://courses.illinois.edu/cisapp/explorer/schedule/2017/spring.xml", "id": "120171", "content": "Spring 2017"}, "subject": {"href": "http://courses.illinois.edu/cisapp/explorer/schedule/2017/spring/MATH.xml", "id": "MATH", "content": "Mathematics"}, "course": {"href": "http://courses.illinois.edu/cisapp/explorer/schedule/2017/spring/MATH/595.xml", "id": "595", "content": "Advanced Topics in Math"}}, "sectionNumber": "ELI", "sectionTitle": "Equity Linked Insurance", "creditHours": "4 hours", "statusCode": "A", "sectionText": "Equity-Linked Linked Insurance.  See http://www.math.uiuc.edu/timetable/  for the full course description.Restricted to Graduate - Urbana-Champaign. Not intended for MS:Economics:Policy Econ -UIUC, MS:Economics:Policy Econ -UIUC, MS: Financial Engineering, MENG:Mechanical Enginerng-UIUC, MENG:Elec & Computer Eng-UIUC, or MENG:Engineering:Comp Eng-UIUC", "sectionNotes": "Restricted to MS:Economics:Policy Econ -UIUC, MS:App Mth-Actuarial Sci -UIUC, or MS: Financial Engineering.", "partOfTerm": "1", "sectionStatusCode": "A", "enrollmentStatus": "CrossListOpen (Restricted)", "startDate": "2017-01-17-06:00", "endDate": "2017-05-03-05:00", "meetings": {"meeting": {"id": "0", "type": {"code": "LCD", "content": "Lecture-Discussion"}, "start": "09:30 AM", "end": "10:50 AM", "daysOfTheWeek": "TR", "roomNumber": "1103", "buildingName": "Siebel Center for Comp Sci", "instructors": {"instructor": {"firstName": "R", "lastName": "Feng", "content": "Feng, R"}}}}}