{"href": "http://courses.illinois.edu/cisapp/explorer/schedule/2017/spring/ART/105/63978.xml", "id": "63978", "parents": {"calendarYear": {"href": "http://courses.illinois.edu/cisapp/explorer/schedule/2017.xml", "id": "2017", "content": "2017"}, "term": {"href": "http://courses.illinois.edu/cisapp/explorer/schedule/2017/spring.xml", "id": "120171", "content": "Spring 2017"}, "subject": {"href": "http://courses.illinois.edu/cisapp/explorer/schedule/2017/spring/ART.xml", "id": "ART", "content": "Art"}, "course": {"href": "http://courses.illinois.edu/cisapp/explorer/schedule/2017/spring/ART/105.xml", "id": "105", "content": "Visual Design for Non-Majors"}}, "sectionNumber": "B", "sectionDateRange": "Meets 13-Mar-17 - 03-May-17.", "statusCode": "A", "partOfTerm": "B", "sectionStatusCode": "A", "enrollmentStatus": "Closed", "startDate": "2017-03-13-05:00", "endDate": "2017-05-03-05:00", "meetings": {"meeting": {"id": "0", "type": {"code": "LAB", "content": "Laboratory"}, "start": "09:30 AM", "end": "10:50 AM", "daysOfTheWeek": "TR", "roomNumber": "131", "buildingName": "Flagg Hall", "instructors": {"instructor": {"firstName": "Q", "lastName": "He", "content": "He, Q"}}}}}