{"href": "http://courses.illinois.edu/cisapp/explorer/schedule/2017/spring/LAST/490.xml", "id": "LAST 490", "parents": {"calendarYear": {"href": "http://courses.illinois.edu/cisapp/explorer/schedule/2017.xml", "id": "2017", "content": "2017"}, "term": {"href": "http://courses.illinois.edu/cisapp/explorer/schedule/2017/spring.xml", "id": "120171", "content": "Spring 2017"}, "subject": {"href": "http://courses.illinois.edu/cisapp/explorer/schedule/2017/spring/LAST.xml", "id": "LAST", "content": "Latin American and Caribbean Studies"}}, "label": "Individual Study", "description": "Major tutorial normally taken in the senior year. Students read the works from list devised in consultation with a faculty tutor and write a term paper. 1 to 5 undergraduate hours. 1 to 5 graduate hours. May be repeated as topics vary to a maximum of 6 hours. Prerequisite: LAST 170; a declared major in Latin American and Caribbean Studies; consent of instructor.", "creditHours": "1 TO 5 hours.", "courseSectionInformation": "1 to 5 undergraduate hours. 1 to 5 graduate hours. May be repeated as topics vary to a maximum of 6 hours. Prerequisite: LAST 170; a declared major in Latin American and Caribbean Studies; consent of instructor.", "sectionApprovalCode": "Advisor Approval Required", "sections": {"section": {"href": "http://courses.illinois.edu/cisapp/explorer/schedule/2017/spring/LAST/490/10499.xml", "id": "10499"}}}