{"href": "http://courses.illinois.edu/cisapp/explorer/schedule/2017/spring/GCL/125/65051.xml", "id": "65051", "parents": {"calendarYear": {"href": "http://courses.illinois.edu/cisapp/explorer/schedule/2017.xml", "id": "2017", "content": "2017"}, "term": {"href": "http://courses.illinois.edu/cisapp/explorer/schedule/2017/spring.xml", "id": "120171", "content": "Spring 2017"}, "subject": {"href": "http://courses.illinois.edu/cisapp/explorer/schedule/2017/spring/GCL.xml", "id": "GCL", "content": "Grand Challenge Learning"}, "course": {"href": "http://courses.illinois.edu/cisapp/explorer/schedule/2017/spring/GCL/125.xml", "id": "125", "content": "Health and Wellness in Life Sciences"}}, "sectionNumber": "E", "sectionTitle": "Sci/Bus of Cancer Therapy", "statusCode": "A", "sectionText": "The Science and Business of Cancer Tharapies.", "partOfTerm": "1", "sectionStatusCode": "A", "enrollmentStatus": "Open (Restricted)", "startDate": "2017-01-17-06:00", "endDate": "2017-05-03-05:00", "meetings": {"meeting": {"id": "0", "type": {"code": "LCD", "content": "Lecture-Discussion"}, "start": "02:00 PM", "end": "03:15 PM", "daysOfTheWeek": "MW", "instructors": {"instructor": {"firstName": "D", "lastName": "Kranz", "content": "Kranz, D"}}}}}