{"href": "http://courses.illinois.edu/cisapp/explorer/schedule/2017/spring/MCB/396.xml", "id": "MCB 396", "parents": {"calendarYear": {"href": "http://courses.illinois.edu/cisapp/explorer/schedule/2017.xml", "id": "2017", "content": "2017"}, "term": {"href": "http://courses.illinois.edu/cisapp/explorer/schedule/2017/spring.xml", "id": "120171", "content": "Spring 2017"}, "subject": {"href": "http://courses.illinois.edu/cisapp/explorer/schedule/2017/spring/MCB.xml", "id": "MCB", "content": "Molecular and Cell Biology"}}, "label": "Special Topics Brain Physiol", "description": "Selected topics in animal physiology. Prerequisite: Credit or concurrent registration in MCB 402; consent of instructor.", "creditHours": "2 hours.", "courseSectionInformation": "Prerequisite: Credit or concurrent registration in MCB 402; consent of instructor.", "sectionApprovalCode": "Instructor Approval Required", "sections": {"section": {"href": "http://courses.illinois.edu/cisapp/explorer/schedule/2017/spring/MCB/396/47574.xml", "id": "47574", "content": "A"}}}