{"courseSectionInformation":"Approved for letter and S/U grading.","creditHours":"0 TO 4 hours.","description":"Training and experience for Ph.D. students in the application of social science and industrial relations theory and research methodology to contemporary industrial relations problems through presentation and discussion of faculty and student research. Ph.D. students are required to make presentations and to participate in workshop discussions during the entire period of their campus residency. Approved for letter and S/U grading.","href":"/2017/spring/LER/558.json","id":"LER 558","label":"Faculty-Student Workshop","parents":{"calendarYear":{"href":"/2017.json","id":"2017","label":"2017"},"subject":{"href":"/2017/spring/LER.json","id":"LER","label":"Labor and Employment Relations"},"term":{"href":"/2017/spring.json","id":"120171","label":"Spring 2017"}},"sections":[{"href":"/2017/spring/LER/558/53441.json","id":"53441","label":"1"}]}
