{"href": "http://courses.illinois.edu/cisapp/explorer/schedule/2017/spring/BADM/449.xml", "id": "BADM 449", "parents": {"calendarYear": {"href": "http://courses.illinois.edu/cisapp/explorer/schedule/2017.xml", "id": "2017", "content": "2017"}, "term": {"href": "http://courses.illinois.edu/cisapp/explorer/schedule/2017/spring.xml", "id": "120171", "content": "Spring 2017"}, "subject": {"href": "http://courses.illinois.edu/cisapp/explorer/schedule/2017/spring/BADM.xml", "id": "BADM", "content": "Business Administration"}}, "label": "Business Policy and Strategy", "description": "Analysis of policy formulation and implementation from a company-wide standpoint; emphasis on integration of knowledge and approaches across functional areas; both endogeneous and exogeneous factors which affect company policies; and the role of the firm in society. 3 undergraduate hours. No graduate credit.", "creditHours": "3 hours.", "courseSectionInformation": "3 undergraduate hours. No graduate credit.", "sectionRegistrationNotes": "Restricted to College of Business. Restricted to students with Senior class standing.", "sections": {"section": [{"href": "http://courses.illinois.edu/cisapp/explorer/schedule/2017/spring/BADM/449/31082.xml", "id": "31082", "content": "A"}, {"href": "http://courses.illinois.edu/cisapp/explorer/schedule/2017/spring/BADM/449/31084.xml", "id": "31084", "content": "B"}, {"href": "http://courses.illinois.edu/cisapp/explorer/schedule/2017/spring/BADM/449/31181.xml", "id": "31181", "content": "E"}, {"href": "http://courses.illinois.edu/cisapp/explorer/schedule/2017/spring/BADM/449/31185.xml", "id": "31185", "content": "G"}, {"href": "http://courses.illinois.edu/cisapp/explorer/schedule/2017/spring/BADM/449/31188.xml", "id": "31188", "content": "I"}, {"href": "http://courses.illinois.edu/cisapp/explorer/schedule/2017/spring/BADM/449/31194.xml", "id": "31194", "content": "L"}, {"href": "http://courses.illinois.edu/cisapp/explorer/schedule/2017/spring/BADM/449/31198.xml", "id": "31198", "content": "M"}, {"href": "http://courses.illinois.edu/cisapp/explorer/schedule/2017/spring/BADM/449/31203.xml", "id": "31203", "content": "O"}, {"href": "http://courses.illinois.edu/cisapp/explorer/schedule/2017/spring/BADM/449/31217.xml", "id": "31217", "content": "S"}, {"href": "http://courses.illinois.edu/cisapp/explorer/schedule/2017/spring/BADM/449/31220.xml", "id": "31220", "content": "T"}]}}