{
    "endDate": "2017-05-03-05:00", 
    "enrollmentStatus": "Open", 
    "href": "/2017/spring/MCB/480/31781.json", 
    "id": "31781", 
    "meetings": {
        "meeting": {
            "daysOfTheWeek": "F", 
            "end": "02:50 PM", 
            "id": "0", 
            "instructors": {
                "instructor": {
                    "content": "Chen, J", 
                    "firstName": "J", 
                    "lastName": "Chen"
                }
            }, 
            "start": "01:00 PM", 
            "type": {
                "code": "LEC", 
                "content": "Lecture"
            }
        }
    }, 
    "parents": {
        "calendarYear": {
            "content": "2017", 
            "href": "/2017.json", 
            "id": "2017"
        }, 
        "course": {
            "content": "Eukaryotic Cell Signaling", 
            "href": "/2017/spring/MCB/480.json", 
            "id": "480"
        }, 
        "subject": {
            "content": "Molecular and Cell Biology", 
            "href": "/2017/spring/MCB.json", 
            "id": "MCB"
        }, 
        "term": {
            "content": "Spring 2017", 
            "href": "/2017/spring.json", 
            "id": "120171"
        }
    }, 
    "partOfTerm": "1", 
    "sectionNumber": "1", 
    "sectionStatusCode": "A", 
    "startDate": "2017-01-17-06:00", 
    "statusCode": "A"
}