{"courseSectionInformation":"Same as CEE 553. See CEE 553.","creditHours":"4 hours.","description":"Same as CEE 553. See CEE 553.","href":"/2017/spring/GEOL/573.json","id":"GEOL 573","label":"River Morphodynamics","parents":{"calendarYear":{"href":"/2017.json","id":"2017","label":"2017"},"subject":{"href":"/2017/spring/GEOL.json","id":"GEOL","label":"Geology"},"term":{"href":"/2017/spring.json","id":"120171","label":"Spring 2017"}},"sections":[{"href":"/2017/spring/GEOL/573/58732.json","id":"58732","label":"G"}]}
