{"href": "http://courses.illinois.edu/cisapp/explorer/schedule/2017/spring/ARTH/299.xml", "id": "ARTH 299", "parents": {"calendarYear": {"href": "http://courses.illinois.edu/cisapp/explorer/schedule/2017.xml", "id": "2017", "content": "2017"}, "term": {"href": "http://courses.illinois.edu/cisapp/explorer/schedule/2017/spring.xml", "id": "120171", "content": "Spring 2017"}, "subject": {"href": "http://courses.illinois.edu/cisapp/explorer/schedule/2017/spring/ARTH.xml", "id": "ARTH", "content": "Art--History"}}, "label": "Spec Topics in Art History", "description": "Special topics in Art History Courses. Topics and subject matter to be published in course listings. May be repeated up to 6 hours in a semester, to a maximum of 12 total hours. Prerequisite: Sophomore standing in Art and Design.", "creditHours": "3 hours.", "courseSectionInformation": "May be repeated up to 6 hours in a semester, to a maximum of 12 total hours. Prerequisite: Sophomore standing in Art and Design.", "sections": {"section": {"href": "http://courses.illinois.edu/cisapp/explorer/schedule/2017/spring/ARTH/299/65136.xml", "id": "65136", "content": "AM"}}}