{"href": "http://courses.illinois.edu/cisapp/explorer/schedule/2017/spring/NRES/427.xml", "id": "NRES 427", "parents": {"calendarYear": {"href": "http://courses.illinois.edu/cisapp/explorer/schedule/2017.xml", "id": "2017", "content": "2017"}, "term": {"href": "http://courses.illinois.edu/cisapp/explorer/schedule/2017/spring.xml", "id": "120171", "content": "Spring 2017"}, "subject": {"href": "http://courses.illinois.edu/cisapp/explorer/schedule/2017/spring/NRES.xml", "id": "NRES", "content": "Natural Resources and Environmental Sciences"}}, "label": "Modeling Natural Resources", "description": "Examines basic modeling concepts and methods. Modeling skills, model development, and natural resource issues and problems will be emphasized. Content areas include fisheries, forests, wildlife, economics, human dimensions, groundwater and surface water. 4 undergraduate hours. 4 graduate hours. Prerequisite: One of MATH 220, MATH 221, MATH 234.", "creditHours": "4 hours.", "courseSectionInformation": "4 undergraduate hours. 4 graduate hours. Prerequisite: One of MATH 220, MATH 221, MATH 234.", "sections": {"section": {"href": "http://courses.illinois.edu/cisapp/explorer/schedule/2017/spring/NRES/427/60538.xml", "id": "60538", "content": "A"}}}