{"endDate":"2017-05-03-05:00","enrollmentStatus":"Open (Restricted)","href":"/2017/spring/SOCW/403/57400.json","id":"57400","meetings":[{"buildingName":"1010 W Nevada","daysOfTheWeek":"TR","end":"10:45 AM","id":"0","instructors":[],"roomNumber":"2030","start":"09:30 AM","type":{"code":"LCD","label":"Lecture-Discussion"}}],"parents":{"calendarYear":{"href":"/2017.json","id":"2017","label":"2017"},"course":{"href":"/2017/spring/SOCW/403.json","id":"403","label":"Practice III"},"subject":{"href":"/2017/spring/SOCW.json","id":"SOCW","label":"Social Work"},"term":{"href":"/2017/spring.json","id":"120171","label":"Spring 2017"}},"partOfTerm":"1","sectionNumber":"A","sectionStatusCode":"A","startDate":"2017-01-17-06:00","statusCode":"A"}
