{"courseSectionInformation":"Prerequisite: MSE 401.","creditHours":"3 OR 4 hours.","description":"Microscopic statistical treatment of the structure and dynamics of polymers, colloids, gels, and other soft materials. Fundamental connections between molecular architecture, intermolecular forces, collective fluid structure, and time-dependent phenomena; Brownian motion, Langevin equation theory, and viscoelasticity; diffusion in colloidal suspensions, gels, and glasses; dynamics of polymer solutions and melts. Prerequisite: MSE 401.","href":"/2017/spring/MSE/583.json","id":"MSE 583","label":"Dynamics of Complex Fluids","parents":{"calendarYear":{"href":"/2017.json","id":"2017","label":"2017"},"subject":{"href":"/2017/spring/MSE.json","id":"MSE","label":"Materials Science and Engineering"},"term":{"href":"/2017/spring.json","id":"120171","label":"Spring 2017"}},"sections":[{"href":"/2017/spring/MSE/583/48166.json","id":"48166","label":"A"}]}
