{"href": "http://courses.illinois.edu/cisapp/explorer/schedule/2017/spring/ENVS/101.xml", "id": "ENVS 101", "parents": {"calendarYear": {"href": "http://courses.illinois.edu/cisapp/explorer/schedule/2017.xml", "id": "2017", "content": "2017"}, "term": {"href": "http://courses.illinois.edu/cisapp/explorer/schedule/2017/spring.xml", "id": "120171", "content": "Spring 2017"}, "subject": {"href": "http://courses.illinois.edu/cisapp/explorer/schedule/2017/spring/ENVS.xml", "id": "ENVS", "content": "Environmental Studies"}}, "label": "Introduction to Energy Sources", "description": "Same as NPRE 101. See NPRE 101.", "creditHours": "3 hours.", "courseSectionInformation": "Same as NPRE 101. See NPRE 101.", "sectionRegistrationNotes": "Restricted to Undergrad - Urbana-Champaign.", "genEdCategories": {"category": [{"id": "NAT", "description": "Natural Sciences & Technology", "{http://rest.cis.illinois.edu}genEdAttributes": {"genEdAttribute": {"code": "1PS", "content": "UIUC: Physical Sciences"}}}, {"id": "QR", "description": "Quantitative Reasoning", "{http://rest.cis.illinois.edu}genEdAttributes": {"genEdAttribute": {"code": "1QR2", "content": "UIUC: Quant Reasoning II"}}}]}, "sections": {"section": [{"href": "http://courses.illinois.edu/cisapp/explorer/schedule/2017/spring/ENVS/101/34667.xml", "id": "34667", "content": "A"}, {"href": "http://courses.illinois.edu/cisapp/explorer/schedule/2017/spring/ENVS/101/34678.xml", "id": "34678", "content": "AL1"}, {"href": "http://courses.illinois.edu/cisapp/explorer/schedule/2017/spring/ENVS/101/34671.xml", "id": "34671", "content": "AY1"}, {"href": "http://courses.illinois.edu/cisapp/explorer/schedule/2017/spring/ENVS/101/34674.xml", "id": "34674", "content": "AY2"}]}}